MANIFEST.in
README.txt
license.txt
setup.py
Photofile.egg-info/PKG-INFO
Photofile.egg-info/SOURCES.txt
Photofile.egg-info/dependency_links.txt
Photofile.egg-info/not-zip-safe
Photofile.egg-info/requires.txt
Photofile.egg-info/top_level.txt
photofile/__init__.py
photofile/templatetags/__init__.py
photofile/templatetags/photofile_tags.py