Metadata-Version: 1.0
Name: Photofile
Version: 0.1.0
Summary: Templatetags for thumbnail generation, with automatic rotation based on EXIF.Orientation.
Home-page: https://bitbucket.org/weholt/django-photofile
Author: Thomas Weholt
Author-email: thomas@weholt.org
License: GPL
Keywords: photo thumbnail generation django metadata
Platform: UNKNOWN
Classifier: Development Status :: 2 - Pre-Alpha
Classifier: Environment :: Web Environment
Classifier: Framework :: Django
Classifier: Intended Audience :: Developers
Classifier: License :: OSI Approved :: GNU General Public License (GPL)
Classifier: Operating System :: OS Independent
Classifier: Programming Language :: Python
Classifier: Topic :: Utilities
